mkdocs_title_casing_plugin/__init__.py
mkdocs_title_casing_plugin/plugin.py
mkdocs_title_casing_plugin-0.2.0.dist-info/LICENSE
mkdocs_title_casing_plugin-0.2.0.dist-info/METADATA
mkdocs_title_casing_plugin-0.2.0.dist-info/WHEEL
mkdocs_title_casing_plugin-0.2.0.dist-info/entry_points.txt
mkdocs_title_casing_plugin-0.2.0.dist-info/top_level.txt
mkdocs_title_casing_plugin-0.2.0.dist-info/RECORD
