Metadata-Version: 2.1
Name: mkdocs-title-casing-plugin
Version: 0.2.0
Summary: A lightweight mkdocs plugin to add title casing to all mkdocs pages and sections
Home-page: https://github.com/Rusty3141/mkdocs-title-casing-plugin
Author: Rusty3141
License: GPLv3
Keywords: mkdocs title case casing plugin
Platform: UNKNOWN
Classifier: Programming Language :: Python :: 3
Classifier: Programming Language :: Python :: 3.6
Classifier: Programming Language :: Python :: 3.7
Classifier: Programming Language :: Python :: 3.8
Classifier: Programming Language :: Python :: 3.9
Classifier: License :: OSI Approved :: GNU General Public License v3 (GPLv3)
Classifier: Operating System :: OS Independent
Requires-Python: >=3.6
Requires-Dist: mkdocs (>=1.0)
Requires-Dist: titlecase (>=2.3)
